wolkenatlas/__init__.py
wolkenatlas/constants.py
wolkenatlas/download.py
wolkenatlas/embedding.py
wolkenatlas/encoder.py
wolkenatlas/preprocessing.py
wolkenatlas/util/__init__.py
wolkenatlas/util/data_processing.py
wolkenatlas/util/file_processing.py
wolkenatlas-0.2.4.dist-info/LICENSE
wolkenatlas-0.2.4.dist-info/METADATA
wolkenatlas-0.2.4.dist-info/WHEEL
wolkenatlas-0.2.4.dist-info/top_level.txt
wolkenatlas-0.2.4.dist-info/RECORD
