Metadata-Version: 2.1
Name: wolkenatlas
Version: 0.2.4
Summary: NLP embedding wrapper
Home-page: https://github.com/tttthomasssss/wolkenatlas
Author: Thomas Kober
Author-email: Thomas Kober <tttthomasssss@gmail.com>
License: MIT License
Project-URL: Homepage, https://github.com/tttthomasssss/wolkenatlas
Project-URL: Bug Tracker, https://github.com/tttthomasssss/wolkenatlas/issues
Classifier: Programming Language :: Python :: 3
Classifier: License :: OSI Approved :: MIT License
Classifier: Operating System :: OS Independent
Classifier: Intended Audience :: Science/Research
Classifier: Topic :: Scientific/Engineering :: Artificial Intelligence
Requires-Python: >=3.8
License-File: LICENSE
